README.md
setup.py
SongUtils/AVAUtils.py
SongUtils/BoxUtils.py
SongUtils/DistUtils.py
SongUtils/FSUtils.py
SongUtils/IOUtils.py
SongUtils/MetricUtils.py
SongUtils/MiscUtils.py
SongUtils/PltUtils.py
SongUtils/__init__.py
SongUtils.egg-info/PKG-INFO
SongUtils.egg-info/SOURCES.txt
SongUtils.egg-info/dependency_links.txt
SongUtils.egg-info/requires.txt
SongUtils.egg-info/top_level.txt
SongUtils/MLUtils/BaseArgs.py
SongUtils/MLUtils/BaseTrainers.py
SongUtils/MLUtils/__init__.py
SongUtils/MLUtils/train_mnist.py