Metadata-Version: 2.1
Name: SongUtils
Version: 0.0.8
Summary: Junjie's private utils.
Home-page: https://github.com/Adenialzz/SongUtils
Author: Adenialzz
Author-email: 1160180309@qq.com
License: MIT Licence
Keywords: pip,SongUtils
Platform: any
